certbot_dns_selectel/__init__.py
certbot_dns_selectel/dns_selectel.py
certbot_dns_selectel/dns_selectel_test.py
certbot_dns_selectel-0.0.1.dist-info/LICENSE
certbot_dns_selectel-0.0.1.dist-info/METADATA
certbot_dns_selectel-0.0.1.dist-info/WHEEL
certbot_dns_selectel-0.0.1.dist-info/entry_points.txt
certbot_dns_selectel-0.0.1.dist-info/top_level.txt
certbot_dns_selectel-0.0.1.dist-info/RECORD
