Metadata-Version: 2.1
Name: certbot-dns-selectel
Version: 0.0.1
Summary: Selectel DNS Authenticator plugin for Certbot
Home-page: https://github.com/Shm013/certbot-dns-selectel
Author: Nikolay Shamanovich
Author-email: shm013@yandex.ru
License: Apache License 2.0
Platform: UNKNOWN
Classifier: Development Status :: 3 - Alpha
Classifier: Environment :: Plugins
Classifier: Intended Audience :: System Administrators
Classifier: License :: OSI Approved :: Apache Software License
Classifier: Operating System :: POSIX :: Linux
Classifier: Programming Language :: Python
Classifier: Programming Language :: Python :: 2
Classifier: Programming Language :: Python :: 2.7
Classifier: Programming Language :: Python :: 3
Classifier: Programming Language :: Python :: 3.4
Classifier: Programming Language :: Python :: 3.5
Classifier: Programming Language :: Python :: 3.6
Classifier: Programming Language :: Python :: 3.7
Classifier: Programming Language :: Python :: 3.8
Classifier: Topic :: Internet :: WWW/HTTP
Classifier: Topic :: Security
Classifier: Topic :: System :: Installation/Setup
Classifier: Topic :: System :: Networking
Classifier: Topic :: System :: Systems Administration
Classifier: Topic :: Utilities
Requires-Python: >=2.7, !=3.0.*, !=3.1.*, !=3.2.*, !=3.3.*
Requires-Dist: acme (>=0.29.0)
Requires-Dist: certbot (>=0.39.0)
Requires-Dist: selectel-dns-api
Requires-Dist: mock
Requires-Dist: setuptools
Requires-Dist: zope.interface
Provides-Extra: docs
Requires-Dist: Sphinx (>=1.0) ; extra == 'docs'
Requires-Dist: sphinx-rtd-theme ; extra == 'docs'
